{
  "ferramentas": [
    {
      "id": "meu-ip",
      "nome": "Meu IP",
      "descricao": "Consulta de IP público e dados de geolocalização.",
      "icone": "user"
    },
    {
      "id": "ping",
      "nome": "Teste de Ping",
      "descricao": "Mede a latência e disponibilidade de um host via pacotes ICMP.",
      "icone": "activity"
    },
    {
      "id": "traceroute",
      "nome": "Traceroute",
      "descricao": "Mapeia o caminho e os saltos de rede até o destino.",
      "icone": "route"
    },
    {
      "id": "nslookup",
      "nome": "NSLookup",
      "descricao": "Consulte registros de servidores DNS para domínios.",
      "icone": "database"
    },
    {
      "id": "dns-lookup",
      "nome": "DNS Lookup",
      "descricao": "Consulta registros DNS para domínios específicos.",
      "icone": "globe"
    },
    {
      "id": "ip-geolocation",
      "nome": "IP Geolocation",
      "descricao": "Determina a localização geográfica de um endereço IP.",
      "icone": "map-pin"
    },
    {
      "id": "port-scanner",
      "nome": "Port Scanner",
      "descricao": "Escaneia portas abertas em um host para segurança de rede.",
      "icone": "shield"
    },
    {
      "id": "ssl-checker",
      "nome": "SSL Checker",
      "descricao": "Verifica a validade e configuração de certificados SSL.",
      "icone": "lock"
    },
    {
      "id": "whois",
      "nome": "WHOIS",
      "descricao": "Consulta informações de registro de domínios e IPs.",
      "icone": "info"
    }, 
    {
      "id": "http-header-checker",
      "nome": "HTTP Header Checker",
      "descricao": "Analisa os cabeçalhos HTTP de um site para diagnóstico.",
      "icone": "server"
    },
    {
      "id": "ip-reputation-checker",
      "nome": "IP Reputation Checker",
      "descricao": "Avalia a reputação de um endereço IP com base em listas de bloqueio e relatórios de segurança.",
      "icone": "shield-x"
    },
 
    {
      "id": "ip-blacklist-checker",
      "nome": "IP Blacklist Checker",
      "descricao": "Verifica se um endereço IP está listado em bancos de dados de bloqueio de spam ou segurança.",
      "icone": "shield-off"
    }

  ],
  "users": []
}